LICENSE
cfgman/__init__.py
cfgman/errors.py
cfgman/loaders/__init__.py
cfgman/loaders/env.py
cfgman/loaders/file.py
cfgman/py.typed
cfgman/tree.py
cfgman/types.py
cfgman-0.2.1.dist-info/LICENSE
cfgman-0.2.1.dist-info/WHEEL
cfgman-0.2.1.dist-info/METADATA
cfgman-0.2.1.dist-info/RECORD
