Metadata-Version: 2.1
Name: cfgman
Version: 0.2.1
Summary: Configuration manager made easy.
Home-page: https://duilio.github.io/cfgman/
License: MIT
Keywords: config,settings
Author: Maurizio Sambati
Author-email: maurizio@skicelab.com
Requires-Python: >=3.10,<4.0
Classifier: Development Status :: 3 - Alpha
Classifier: License :: OSI Approved :: MIT License
Classifier: Operating System :: OS Independent
Classifier: Programming Language :: Python
Classifier: Programming Language :: Python :: 3
Classifier: Programming Language :: Python :: 3.10
Classifier: Programming Language :: Python :: 3.10
Classifier: Topic :: Software Development :: Libraries :: Python Modules
Provides-Extra: all
Provides-Extra: toml
Provides-Extra: yaml
Requires-Dist: PyYAML (>=6.0,<7.0); extra == "yaml" or extra == "all"
Requires-Dist: apischema (>=0.17.5,<0.18.0)
Requires-Dist: pytest (>=7.1.3,<8.0.0)
Requires-Dist: tomli (>=2.0.1,<3.0.0); extra == "toml" or extra == "all"
Project-URL: Repository, https://github.com/duilio/cfgman
